{
  "name": "Scroll Badges",
  "timestamp": "2024-07-14T14:56:48.996Z",
  "badges": [
    {
      "name": "Zebra",
      "image": "https://app.zebra.xyz/images/badge.png",
      "description": "Users who participate in Scroll Canvas and complete tasks will receive Zebra's 'zebra' badge. Users with this badge will enjoy Zebra's early benefits in the future.",
      "attesterProxy": "0x35BcDcd5813a08f890163c166826856B47e7977F",
      "badgeContract": "0x09E14E520eec3583681Fe225a4B506743EC3cc78",
      "issuer": {
        "name": "Zebra",
        "logo": "https://scroll-eco-list.netlify.app/logos/Zebra.png",
        "origin": "https://app.zebra.xyz/"
      },
      "baseUrl": "https://zebra.xyz/api/badge",
      "native": false
    },
    {
      "name": "Unrevealed",
      "image": "https://cyan-passive-guan-475.mypinata.cloud/ipfs/QmY9rG94E1qpc5NPs1zFTM1hCCTmv9kiRvMoZjGyxCJ2ZE/0.png",
      "description": "Unrevealed scrolly badge.",
      "attesterProxy": "0x47a49cCfa1924D5b59cb400708199b6Ae8543D31",
      "badgeContract": "0x79b4f7492328D0Cc4ED0Ddaee08Cd42f0F36A4CC",
      "issuer": {
        "name": "Scrolly",
        "logo": "https://scroll-eco-list.netlify.app/logos/Scrolly.jpg",
        "origin": "https://hub.scrolly.xyz/"
      },
      "baseUrl": "https://api.scrolly.xyz/api/badge",
      "native": false
    }
  ]
}
